README.rst
setup.py
bin/donkey_kong
donkey_kong/__init__.py
donkey_kong/credentials.py
donkey_kong/main.py
donkey_kong.egg-info/PKG-INFO
donkey_kong.egg-info/SOURCES.txt
donkey_kong.egg-info/dependency_links.txt
donkey_kong.egg-info/requires.txt
donkey_kong.egg-info/top_level.txt