Metadata-Version: 1.0
Name: donkey-kong
Version: 0.1
Summary: Send mandrill templates from the command line.
Home-page: https://github.com/yhat/donkey_kong
Author: Jessie Frazelle
Author-email: jessie@yhathq.com
License: BSD
Keywords: mandrill,mailchimp,email,templates,send
Platform: UNKNOWN
